part1a.v
`timescale 10ps/1ps

module flipFlop(
    input d,clock,
    output q);
    wire mD, mD_bar, mTop, mBot, mQ,mQ_bar, clock_bar,
    sD, sD_bar, sTop, sBot, sQ, sQ_bar;

    not(clock_bar,clock);
    not(mD_bar,mD);
    notif1(mD,d,clock_bar);
    nand(mTop,mD,clock_bar);
    nand(mBot,mD_bar,clock_bar);
    nand(mQ,mTop,mQ_bar);
    nand(mQ_bar,mBot,mQ);

    not(sD_bar,sD);
    notif1(sD,mQ,clock);
    nand(sTop,sD,clock);
    nand(sBot,sD_bar,clock);
    nand(sQ,sTop,sQ_bar);
    nand(sQ_bar,sBot,sQ);
    buf(q,sQ);

endmodule

tb_part1a.v
`timescale 1ns/1ps

module tb_flipFlop;
    wire q;
    reg d, clock;
    integer i;

    flipFlop dat(.d(d),.clock(clock),.q(q));
    initial
        begin
            $dumpfile("wave_flipFlop.vcd");
            $dumpvars(0,tb_flipFlop);
            clock = 0;
                for(i=0; i<30;i=i+1) begin
                    #10 clock = ~clock;
                end
        end
    initial 
        begin
            d = 0;
            #50;
            d = 1;
            #50;
            d = 0;
            #50;
            d = 1;
            #50;
        end
    always @ (d)
        begin
          $display("D = %d, clock = %d", d, clock);
        end
endmodule

wave_flipFlop.vcd
$date
	Thu Apr 18 22:55:33 2024
$end
$version
	Icarus Verilog
$end
$timescale
	1ps
$end
$scope module tb_flipFlop $end
$var wire 1 ! q $end
$var reg 1 " clock $end
$var reg 1 # d $end
$var integer 32 $ i [31:0] $end
$scope module dat $end
$var wire 1 " clock $end
$var wire 1 % clock_bar $end
$var wire 1 # d $end
$var wire 1 & mBot $end
$var wire 1 ' mD $end
$var wire 1 ( mD_bar $end
$var wire 1 ) mQ $end
$var wire 1 * mQ_bar $end
$var wire 1 + mTop $end
$var wire 1 ! q $end
$var wire 1 , sBot $end
$var wire 1 - sD $end
$var wire 1 . sD_bar $end
$var wire 1 / sQ $end
$var wire 1 0 sQ_bar $end
$var wire 1 1 sTop $end
$upscope $end
$upscope $end
$enddefinitions $end
$comment Show the parameter values. $end
$dumpall
$end
#0
$dumpvars
11
x0
x/
x.
z-
1,
0+
0*
1)
0(
1'
1&
1%
b0 $
0#
0"
x!
$end
#10000
0!
0/
10
x(
1+
z'
0%
1.
0,
b1 $
0-
1"
#20000
0*
0(
0+
1&
1'
1%
x.
1,
b10 $
z-
0"
#30000
x(
1+
z'
0%
1.
0,
b11 $
0-
1"
#40000
0*
0(
0+
1&
1'
1%
x.
1,
b100 $
z-
0"
#50000
0%
1.
0,
1+
x(
b101 $
0-
1"
z'
1#
#60000
0)
1*
1(
0&
0'
1%
x.
1,
b110 $
z-
0"
#70000
00
1!
x(
1&
1/
z'
0%
0.
01
1,
b111 $
1-
1"
#80000
1(
0&
0'
1%
x.
11
b1000 $
z-
0"
#90000
x(
1&
00
z'
0%
0.
01
1,
b1001 $
1-
1"
#100000
0*
1)
0(
0+
1&
1'
1%
x.
11
b1010 $
z-
0"
0#
#110000
0!
0/
x(
1+
10
z'
0%
1.
0,
b1011 $
0-
1"
#120000
0*
0(
0+
1&
1'
1%
x.
1,
b1100 $
z-
0"
#130000
x(
1+
z'
0%
1.
0,
b1101 $
0-
1"
#140000
0*
0(
0+
1&
1'
1%
x.
1,
b1110 $
z-
0"
#150000
0%
1.
0,
1+
x(
b1111 $
0-
1"
z'
1#
#160000
0)
1*
1(
0&
0'
1%
x.
1,
b10000 $
z-
0"
#170000
00
1!
x(
1&
1/
z'
0%
0.
01
1,
b10001 $
1-
1"
#180000
1(
0&
0'
1%
x.
11
b10010 $
z-
0"
#190000
x(
1&
00
z'
0%
0.
01
1,
b10011 $
1-
1"
#200000
1(
0&
0'
1%
x.
11
b10100 $
z-
0"
#210000
x(
1&
00
z'
0%
0.
01
1,
b10101 $
1-
1"
#220000
1(
0&
0'
1%
x.
11
b10110 $
z-
0"
#230000
x(
1&
00
z'
0%
0.
01
1,
b10111 $
1-
1"
#240000
1(
0&
0'
1%
x.
11
b11000 $
z-
0"
#250000
x(
1&
00
z'
0%
0.
01
1,
b11001 $
1-
1"
#260000
1(
0&
0'
1%
x.
11
b11010 $
z-
0"
#270000
x(
1&
00
z'
0%
0.
01
1,
b11011 $
1-
1"
#280000
1(
0&
0'
1%
x.
11
b11100 $
z-
0"
#290000
x(
1&
00
z'
0%
0.
01
1,
b11101 $
1-
1"
#300000
1(
0&
0'
1%
x.
11
b11110 $
z-
0"
