part1a.v
`timescale 1ns/1ps

module flipFlop(
    input d,clock,
    output q);
    wire mD, mD_bar, mTop, mBot, mQ,mQ_bar, clock_bar,
    sD, sD_bar, sTop, sBot, sQ, sQ_bar;

    not(clock_bar,clock);
    not(mD_bar,mD);
    notif1(mD,d,clock_bar);
    nand(mTop,mD,clock_bar);
    nand(mBot,mD_bar,clock_bar);
    nand(mQ,mTop,mQ_bar);
    nand(mQ_bar,mBot,mQ);

    not(sD_bar,sD);
    notif1(sD,mQ,clock);
    nand(sTop,sD,clock);
    nand(sBot,sD_bar,clock);
    nand(sQ,sTop,sQ_bar);
    nand(sQ_bar,sBot,sQ);
    buf(q,sQ);

endmodule

part2a.v
`timescale 1ns/1ps
`include "part1a.v"

module register(
    input new_D, clock, en, 
    output Q);

    wire D, en_bar, w1,w2;
    not(en_bar, en);
    and(w1,en_bar, Q);
    and(w2,en, new_D);
    or(D,w1,w2);
    flipFlop ff(.d(D),.clock(clock),.q(Q));

endmodule

tb_part2a.v
`timescale 1ns/1ps

module tb_register;
    wire Q;
    reg new_D, clock, en;
    integer i,j;

    register dat(.new_D(new_D),.clock(clock),.Q(Q),.en(en));
    initial
        begin
            $dumpfile("wave_register.vcd");
            $dumpvars(0,tb_register);
            clock = 0;
                for(i=0; i<30;i=i+1) begin
                    #10 clock = ~clock;
                end
        end
    initial 
        begin
            new_D = 0;
            en = 1;
            for(j=0;j<12;j=j+1)begin
                #25 new_D = ~ new_D;
                if(j%2==0&&j>0)
                    #5 en = ~ en;
            end
        end
    always @ (new_D)
        begin
          $display("D = %d, clock = %d", new_D, clock);
        end
endmodule

wave_register.vcd
$date
	Thu Apr 18 23:24:31 2024
$end
$version
	Icarus Verilog
$end
$timescale
	1ps
$end
$scope module tb_register $end
$var wire 1 ! Q $end
$var reg 1 " clock $end
$var reg 1 # en $end
$var reg 1 $ new_D $end
$var integer 32 % i [31:0] $end
$var integer 32 & j [31:0] $end
$scope module dat $end
$var wire 1 ' D $end
$var wire 1 " clock $end
$var wire 1 # en $end
$var wire 1 ( en_bar $end
$var wire 1 $ new_D $end
$var wire 1 ) w1 $end
$var wire 1 * w2 $end
$var wire 1 ! Q $end
$scope module ff $end
$var wire 1 " clock $end
$var wire 1 + clock_bar $end
$var wire 1 ' d $end
$var wire 1 , mBot $end
$var wire 1 - mD $end
$var wire 1 . mD_bar $end
$var wire 1 / mQ $end
$var wire 1 0 mQ_bar $end
$var wire 1 1 mTop $end
$var wire 1 ! q $end
$var wire 1 2 sBot $end
$var wire 1 3 sD $end
$var wire 1 4 sD_bar $end
$var wire 1 5 sQ $end
$var wire 1 6 sQ_bar $end
$var wire 1 7 sTop $end
$upscope $end
$upscope $end
$upscope $end
$enddefinitions $end
$comment Show the parameter values. $end
$dumpall
$end
#0
$dumpvars
17
x6
x5
x4
z3
12
01
00
1/
0.
1-
1,
1+
0*
0)
0(
0'
b0 &
b0 %
0$
1#
0"
x!
$end
#10000
0!
05
16
x.
11
z-
0+
14
02
b1 %
03
1"
#20000
00
0.
01
1,
1-
1+
x4
12
b10 %
z3
0"
#25000
0/
10
0,
11
1.
0-
1'
1*
b1 &
1$
#30000
06
1!
x.
1,
15
z-
0+
04
07
12
b11 %
13
1"
#40000
1.
0,
0-
1+
x4
17
b100 %
z3
0"
#50000
x.
1,
06
0'
z-
0+
04
07
12
0*
b101 %
13
1"
b10 &
0$
#60000
00
1/
0.
01
1,
1-
1+
x4
17
b110 %
z3
0"
#70000
0!
05
x.
11
16
z-
0+
14
02
b111 %
03
1"
#75000
1'
1*
1$
#80000
01
00
0'
0.
1,
1(
0*
1-
1+
x4
12
b11 &
0#
b1000 %
z3
0"
#90000
x.
11
z-
0+
14
02
b1001 %
03
1"
#100000
00
0.
01
1,
1-
1+
x4
12
b1010 %
z3
0"
#105000
b100 &
0$
#110000
x.
11
z-
0+
14
02
b1011 %
03
1"
#120000
00
0.
01
1,
1-
1+
x4
12
b1100 %
z3
0"
#130000
x.
11
z-
0+
14
02
b1101 %
03
1"
1$
#135000
1'
0(
1*
b101 &
1#
#140000
0/
10
1.
0,
0-
1+
x4
12
b1110 %
z3
0"
#150000
06
1!
x.
1,
15
z-
0+
04
07
12
b1111 %
13
1"
#160000
00
1/
0.
01
1,
0'
1-
1+
x4
17
0*
b10000 %
z3
0"
b110 &
0$
#170000
0!
05
x.
11
16
z-
0+
14
02
b10001 %
03
1"
#180000
00
0.
01
1,
1-
1+
x4
12
b10010 %
z3
0"
#185000
0/
10
0,
11
1.
0-
1'
1*
1$
#190000
1)
06
1!
1'
x.
1,
15
1(
0*
z-
0+
04
07
12
b111 &
0#
b10011 %
13
1"
#200000
1.
0,
0-
1+
x4
17
b10100 %
z3
0"
#210000
x.
1,
06
z-
0+
04
07
12
b10101 %
13
1"
#215000
b1000 &
0$
#220000
1.
0,
0-
1+
x4
17
b10110 %
z3
0"
#230000
x.
1,
06
z-
0+
04
07
12
b10111 %
13
1"
#240000
1.
0,
0-
1+
x4
17
b11000 %
z3
0"
1$
#245000
0)
0(
1*
b1001 &
1#
#250000
x.
1,
06
z-
0+
04
07
12
b11001 %
13
1"
#260000
1.
0,
0-
1+
x4
17
b11010 %
z3
0"
#270000
x.
1,
06
0'
z-
0+
04
07
12
0*
b11011 %
13
1"
b1010 &
0$
#280000
00
1/
0.
01
1,
1-
1+
x4
17
b11100 %
z3
0"
#290000
0!
05
x.
11
16
z-
0+
14
02
b11101 %
03
1"
#295000
1'
1*
1$
#300000
01
00
0'
0.
1,
1(
0*
1-
1+
x4
12
b1011 &
0#
b11110 %
z3
0"
#325000
b1100 &
0$
