part1b.v
`timescale 1ns/1ps

module flipFlop(
    input d,clock,reset,
    output q, q_bar);
    reg q,q_bar;

    always @ (posedge clock or negedge reset)
        begin
        if(reset == 0) begin
            q<=0;
            q_bar<= 1;
        end
        else begin
            q<=d;
            q_bar <= ~d;
        end
    end
endmodule

tb_part1b.v
`timescale 1ns/1ps

module tb_flipFlop;
    wire q,q_bar;
    reg d, clock,reset;
    integer i,j;

    flipFlop dat(.d(d),.clock(clock),.q(q),.q_bar(q_bar),.reset(reset));
    initial
        begin
            $dumpfile("wave_flipFlopRest.vcd");
            $dumpvars(0,tb_flipFlop);
            clock = 0;
                for(i=0; i<30;i=i+1) begin
                    #10 clock = ~clock;
                end
            reset = 1;
        end
    initial 
        begin
            d = 0;
            reset = 1;
            for(j=0;j<12;j=j+1)begin
                #25 d = ~ d;
                if(j%4==0&&j>0)
                    reset = ~ reset;
            end
            
        end
    always @ (d)
        begin
          $display("D = %d, clock = %d", d, clock);
        end
endmodule

wave_flipFlopRest.vcd
$date
	Thu Apr 18 14:56:59 2024
$end
$version
	Icarus Verilog
$end
$timescale
	1ps
$end
$scope module tb_flipFlop $end
$var wire 1 ! q_bar $end
$var wire 1 " q $end
$var reg 1 # clock $end
$var reg 1 $ d $end
$var reg 1 % reset $end
$var integer 32 & i [31:0] $end
$var integer 32 ' j [31:0] $end
$scope module dat $end
$var wire 1 # clock $end
$var wire 1 $ d $end
$var wire 1 % reset $end
$var reg 1 " q $end
$var reg 1 ! q_bar $end
$upscope $end
$upscope $end
$enddefinitions $end
$comment Show the parameter values. $end
$dumpall
$end
#0
$dumpvars
b0 '
b0 &
1%
0$
0#
x"
x!
$end
#10000
1!
0"
b1 &
1#
#20000
b10 &
0#
#25000
b1 '
1$
#30000
0!
1"
b11 &
1#
#40000
b100 &
0#
#50000
1!
0"
b101 &
1#
b10 '
0$
#60000
b110 &
0#
#70000
b111 &
1#
#75000
b11 '
1$
#80000
b1000 &
0#
#90000
0!
1"
b1001 &
1#
#100000
b1010 &
0#
b100 '
0$
#110000
1!
0"
b1011 &
1#
#120000
b1100 &
0#
#125000
b101 '
0%
1$
#130000
b1101 &
1#
#140000
b1110 &
0#
#150000
b1111 &
1#
b110 '
0$
#160000
b10000 &
0#
#170000
b10001 &
1#
#175000
b111 '
1$
#180000
b10010 &
0#
#190000
b10011 &
1#
#200000
b10100 &
0#
b1000 '
0$
#210000
b10101 &
1#
#220000
b10110 &
0#
#225000
b1001 '
1%
1$
#230000
0!
1"
b10111 &
1#
#240000
b11000 &
0#
#250000
1!
0"
b11001 &
1#
b1010 '
0$
#260000
b11010 &
0#
#270000
b11011 &
1#
#275000
b1011 '
1$
#280000
b11100 &
0#
#290000
0!
1"
b11101 &
1#
#300000
b11110 &
0#
b1100 '
0$
